frozenlake_demo/__init__.py
frozenlake_demo/frozen_lake.py
frozenlake_demo-0.0.3.dist-info/METADATA
frozenlake_demo-0.0.3.dist-info/WHEEL
frozenlake_demo-0.0.3.dist-info/top_level.txt
frozenlake_demo-0.0.3.dist-info/RECORD
