Metadata-Version: 2.4
Name: frozenlake-demo
Version: 0.0.3
Summary: A minimal FrozenLake environment with custom BaseEnv
Author-email: User <user@example.com>
License: MIT
Project-URL: Homepage, https://github.com/example/frozenlake-demo
Requires-Python: >=3.8
Requires-Dist: numpy>=1.21.0
